dataplaybook/__init__.py
dataplaybook/__main__.py
dataplaybook/const.py
dataplaybook/everything.py
dataplaybook/helper.py
dataplaybook/helpers/__init__.py
dataplaybook/helpers/args.py
dataplaybook/helpers/env.py
dataplaybook/helpers/typeh.py
dataplaybook/main.py
dataplaybook/py.typed
dataplaybook/tasks/__init__.py
dataplaybook/tasks/all.py
dataplaybook/tasks/fnb.py
dataplaybook/tasks/fuzzy.py
dataplaybook/tasks/gis.py
dataplaybook/tasks/ietf.py
dataplaybook/tasks/io_mail.py
dataplaybook/tasks/io_misc.py
dataplaybook/tasks/io_mongo.py
dataplaybook/tasks/io_pdf.py
dataplaybook/tasks/io_pptx.py
dataplaybook/tasks/io_xlsx.py
dataplaybook/tasks/io_xml.py
dataplaybook/utils/__init__.py
dataplaybook/utils/ensure.py
dataplaybook/utils/lists.py
dataplaybook/utils/logger.py
dataplaybook/utils/parser/__init__.py
dataplaybook/utils/parser/convert.py
dataplaybook/utils/parser/parse.py
dataplaybook-1.1.16.dist-info/WHEEL
dataplaybook-1.1.16.dist-info/entry_points.txt
dataplaybook-1.1.16.dist-info/METADATA
dataplaybook-1.1.16.dist-info/RECORD
