Metadata-Version: 2.3
Name: dataplaybook
Version: 1.1.16
Summary: Playbooks for data. Open, process and save table based data.
Keywords: data,excel,generators,mongodb,tables
Author: Johann Kellerman
Author-email: Johann Kellerman <kellerza@gmail.com>
License:                                  Apache License
Classifier: Development Status :: 2 - Pre-Alpha
Classifier: Intended Audience :: Developers
Classifier: Natural Language :: English
Classifier: Programming Language :: Python :: 3 :: Only
Classifier: Programming Language :: Python :: 3.12
Classifier: Programming Language :: Python :: 3.13
Classifier: Programming Language :: Python :: 3.14
Requires-Dist: attrs>=25,<26
Requires-Dist: cattrs>=24,<26
Requires-Dist: colordict>=1.2.6
Requires-Dist: colorlog>=6,<7
Requires-Dist: fuzzywuzzy
Requires-Dist: icecream
Requires-Dist: jinja2>=3,<4
Requires-Dist: office365-rest-python-client>2,<3
Requires-Dist: openpyxl==3.1.5
Requires-Dist: python-levenshtein
Requires-Dist: requests>=2,<3
Requires-Dist: typeguard>=4.4.2
Requires-Dist: whenever>=0.9,<1
Requires-Dist: lxml>=5.4,<7 ; extra == 'all'
Requires-Dist: pymongo>=4,<5 ; extra == 'all'
Requires-Dist: python-pptx ; extra == 'all'
Requires-Python: >=3.12
Project-URL: Homepage, https://github.com/kellerza/data-playbook
Project-URL: Repository, https://github.com/kellerza/data-playbook
Provides-Extra: all
